colored_print/__init__.py
colored_print/colored_print.py
python_colored_print-1.1.0.dist-info/LICENSE
python_colored_print-1.1.0.dist-info/METADATA
python_colored_print-1.1.0.dist-info/WHEEL
python_colored_print-1.1.0.dist-info/top_level.txt
python_colored_print-1.1.0.dist-info/RECORD
