Metadata-Version: 2.1
Name: python_colored_print
Version: 1.1.0
Summary: A simple python library in order to print in different colorsand save them into a file optionally.
Home-page: https://github.com/agn-7/colored-print
Author: agn-7
Author-email: benyaminjmf@gmail.com
License: MIT
Download-URL: https://github.com/agn-7/colored-print/archive/refs/tags/v1.1.0.zip
Keywords: log,logging,python3,python
Platform: UNKNOWN
Classifier: Programming Language :: Python :: 3
License-File: LICENSE
